justinm/cdk_infra/__init__.py
justinm/cdk_infra/py.typed
justinm/cdk_infra/_jsii/__init__.py
justinm/cdk_infra/_jsii/cdk-infra@0.1.1.jsii.tgz
justinm.cdk_infra-0.1.1.dist-info/LICENSE
justinm.cdk_infra-0.1.1.dist-info/METADATA
justinm.cdk_infra-0.1.1.dist-info/WHEEL
justinm.cdk_infra-0.1.1.dist-info/top_level.txt
justinm.cdk_infra-0.1.1.dist-info/RECORD
